pyenvnoise/utils/__init__.py
pyenvnoise/utils/ptiread.py
pyenvnoise-0.1.2.dist-info/LICENSE
pyenvnoise-0.1.2.dist-info/WHEEL
pyenvnoise-0.1.2.dist-info/METADATA
pyenvnoise-0.1.2.dist-info/RECORD
