Metadata-Version: 2.1
Name: pyenvnoise
Version: 0.1.2
Summary: A package for environmental noise analysis
License: MIT
Author: Phuc D. Nguyen
Author-email: ducphuc.nguyen@flinders.edu.au
Maintainer: Phuc D. Nguyen
Maintainer-email: ducphuc.nguyen@flinders.edu.au
Requires-Python: >=3.7,<4.0
Classifier: License :: OSI Approved :: MIT License
Classifier: Programming Language :: Python :: 3
Classifier: Programming Language :: Python :: 3.7
Classifier: Programming Language :: Python :: 3.8
Classifier: Programming Language :: Python :: 3.9
Requires-Dist: numpy (>=1.18.1)
